virtualenv_tools.py
virtualenv_tools3-3.1.0.dist-info/LICENSE
virtualenv_tools3-3.1.0.dist-info/METADATA
virtualenv_tools3-3.1.0.dist-info/WHEEL
virtualenv_tools3-3.1.0.dist-info/entry_points.txt
virtualenv_tools3-3.1.0.dist-info/top_level.txt
virtualenv_tools3-3.1.0.dist-info/RECORD
