Metadata-Version: 2.1
Name: virtualenv-tools3
Version: 3.1.0
Summary: A set of tools for virtualenv
Home-page: http://github.com/Yelp/virtualenv-tools
Author: Fireteam Ltd.; Yelp, Inc.
Author-email: opensource@yelp.com
License: UNKNOWN
Platform: UNKNOWN
Classifier: License :: OSI Approved :: BSD License
Classifier: Programming Language :: Python
Classifier: Programming Language :: Python :: 3
Classifier: Programming Language :: Python :: 3 :: Only
Classifier: Programming Language :: Python :: Implementation :: CPython
Classifier: Programming Language :: Python :: Implementation :: PyPy
Requires-Python: >=3.8
